requestests/__init__.py
requestests/api.py
requestests/validation_operators.py
requestests/validations.py
requestests-1.1.2.dist-info/DESCRIPTION.rst
requestests-1.1.2.dist-info/METADATA
requestests-1.1.2.dist-info/RECORD
requestests-1.1.2.dist-info/WHEEL
requestests-1.1.2.dist-info/metadata.json
requestests-1.1.2.dist-info/top_level.txt
