Metadata-Version: 2.0
Name: requestests
Version: 1.1.2
Summary: Python HTTP Tests for Humans.
Home-page: http://python-requests.org
Author: Peter Salas
Author-email: psalas@gmail.com
License: Apache 2.0
Keywords: testing,requests,requestests,rest,restest
Platform: UNKNOWN
Classifier: Development Status :: 5 - Production/Stable
Classifier: Intended Audience :: Developers
Classifier: Natural Language :: English
Classifier: License :: OSI Approved :: Apache Software License
Classifier: Programming Language :: Python
Classifier: Programming Language :: Python :: 2.6
Classifier: Programming Language :: Python :: 2.7
Classifier: Programming Language :: Python :: 3
Classifier: Programming Language :: Python :: 3.3
Classifier: Programming Language :: Python :: 3.4
Classifier: Programming Language :: Python :: 3.5
Classifier: Programming Language :: Python :: Implementation :: CPython
Classifier: Programming Language :: Python :: Implementation :: PyPy
Requires-Dist: jsonstruct (>=0.2a1)
Requires-Dist: requests (>=2.7.0)
